Workbook

Sheet README
A1: Detección de vinos muertos — Winerim
A3: 1. Rellena la pestaña 'Análisis' con stock, última venta y rotación.
A4: 2. Ajusta los umbrales en 'Umbrales' según tu realidad.
A5: 3. Revisa el score de prioridad y la acción sugerida.
A6: 4. Usa la pestaña 'Resumen' para ver cuántas referencias requieren intervención.

Sheet Umbrales
A1: Umbrales de diagnóstico
A3: Días desde última venta para alerta | B3: 45
A4: Rotación mensual baja | B4: 2
A5: Capital inmovilizado alto (€) | B5: 200
A6: Margen potencial mínimo (€) | B6: 18

Sheet Análisis
A1: Referencia | B1: Tipo | C1: Stock actual | D1: Días desde última venta | E1: Rotación mensual | F1: Coste unitario (€) | G1: PVP botella (€) | H1: Capital inmovilizado (€) | I1: Margen potencial (€) | J1: Score prioridad | K1: Acción sugerida | L1: Notas
A2: Albariño 2022 | B2: Blanco | C2: 10 | D2: 62 | E2: 1 | F2: 8 | G2: 28 | H2: =IF(OR(C2="",F2=""),"",C2*F2) | I2: =IF(OR(F2="",G2=""),"",G2-F2) | J2: =IF(A2="","",IF(D2>=Umbrales!$B$3,2,0)+IF(E2<=Umbrales!$B$4,2,0)+IF(H2>=Umbrales!$B$5,2,0)+IF(I2>=Umbrales!$B$6,1,0)) | K2: =IF(A2="","",IF(J2>=6,"Retirar",IF(J2=5,"Sacar por copa",IF(J2=4,"Visibilizar","Impulsar")))) | L2: Stock inmóvil
A3: Rioja Reserva | B3: Tinto | C3: 4 | D3: 18 | E3: 3 | F3: 14 | G3: 42 | H3: =IF(OR(C3="",F3=""),"",C3*F3) | I3: =IF(OR(F3="",G3=""),"",G3-F3) | J3: =IF(A3="","",IF(D3>=Umbrales!$B$3,2,0)+IF(E3<=Umbrales!$B$4,2,0)+IF(H3>=Umbrales!$B$5,2,0)+IF(I3>=Umbrales!$B$6,1,0)) | K3: =IF(A3="","",IF(J3>=6,"Retirar",IF(J3=5,"Sacar por copa",IF(J3=4,"Visibilizar","Impulsar")))) | L3: Todavía sano
A4: Cava Reserva | B4: Espumoso | C4: 7 | D4: 51 | E4: 2 | F4: 9 | G4: 31 | H4: =IF(OR(C4="",F4=""),"",C4*F4) | I4: =IF(OR(F4="",G4=""),"",G4-F4) | J4: =IF(A4="","",IF(D4>=Umbrales!$B$3,2,0)+IF(E4<=Umbrales!$B$4,2,0)+IF(H4>=Umbrales!$B$5,2,0)+IF(I4>=Umbrales!$B$6,1,0)) | K4: =IF(A4="","",IF(J4>=6,"Retirar",IF(J4=5,"Sacar por copa",IF(J4=4,"Visibilizar","Impulsar")))) | L4: Activar maridaje
H5: =IF(OR(C5="",F5=""),"",C5*F5) | I5: =IF(OR(F5="",G5=""),"",G5-F5) | J5: =IF(A5="","",IF(D5>=Umbrales!$B$3,2,0)+IF(E5<=Umbrales!$B$4,2,0)+IF(H5>=Umbrales!$B$5,2,0)+IF(I5>=Umbrales!$B$6,1,0)) | K5: =IF(A5="","",IF(J5>=6,"Retirar",IF(J5=5,"Sacar por copa",IF(J5=4,"Visibilizar","Impulsar"))))
H6: =IF(OR(C6="",F6=""),"",C6*F6) | I6: =IF(OR(F6="",G6=""),"",G6-F6) | J6: =IF(A6="","",IF(D6>=Umbrales!$B$3,2,0)+IF(E6<=Umbrales!$B$4,2,0)+IF(H6>=Umbrales!$B$5,2,0)+IF(I6>=Umbrales!$B$6,1,0)) | K6: =IF(A6="","",IF(J6>=6,"Retirar",IF(J6=5,"Sacar por copa",IF(J6=4,"Visibilizar","Impulsar"))))
H7: =IF(OR(C7="",F7=""),"",C7*F7) | I7: =IF(OR(F7="",G7=""),"",G7-F7) | J7: =IF(A7="","",IF(D7>=Umbrales!$B$3,2,0)+IF(E7<=Umbrales!$B$4,2,0)+IF(H7>=Umbrales!$B$5,2,0)+IF(I7>=Umbrales!$B$6,1,0)) | K7: =IF(A7="","",IF(J7>=6,"Retirar",IF(J7=5,"Sacar por copa",IF(J7=4,"Visibilizar","Impulsar"))))
H8: =IF(OR(C8="",F8=""),"",C8*F8) | I8: =IF(OR(F8="",G8=""),"",G8-F8) | J8: =IF(A8="","",IF(D8>=Umbrales!$B$3,2,0)+IF(E8<=Umbrales!$B$4,2,0)+IF(H8>=Umbrales!$B$5,2,0)+IF(I8>=Umbrales!$B$6,1,0)) | K8: =IF(A8="","",IF(J8>=6,"Retirar",IF(J8=5,"Sacar por copa",IF(J8=4,"Visibilizar","Impulsar"))))
H9: =IF(OR(C9="",F9=""),"",C9*F9) | I9: =IF(OR(F9="",G9=""),"",G9-F9) | J9: =IF(A9="","",IF(D9>=Umbrales!$B$3,2,0)+IF(E9<=Umbrales!$B$4,2,0)+IF(H9>=Umbrales!$B$5,2,0)+IF(I9>=Umbrales!$B$6,1,0)) | K9: =IF(A9="","",IF(J9>=6,"Retirar",IF(J9=5,"Sacar por copa",IF(J9=4,"Visibilizar","Impulsar"))))
H10: =IF(OR(C10="",F10=""),"",C10*F10) | I10: =IF(OR(F10="",G10=""),"",G10-F10) | J10: =IF(A10="","",IF(D10>=Umbrales!$B$3,2,0)+IF(E10<=Umbrales!$B$4,2,0)+IF(H10>=Umbrales!$B$5,2,0)+IF(I10>=Umbrales!$B$6,1,0)) | K10: =IF(A10="","",IF(J10>=6,"Retirar",IF(J10=5,"Sacar por copa",IF(J10=4,"Visibilizar","Impulsar"))))
H11: =IF(OR(C11="",F11=""),"",C11*F11) | I11: =IF(OR(F11="",G11=""),"",G11-F11) | J11: =IF(A11="","",IF(D11>=Umbrales!$B$3,2,0)+IF(E11<=Umbrales!$B$4,2,0)+IF(H11>=Umbrales!$B$5,2,0)+IF(I11>=Umbrales!$B$6,1,0)) | K11: =IF(A11="","",IF(J11>=6,"Retirar",IF(J11=5,"Sacar por copa",IF(J11=4,"Visibilizar","Impulsar"))))
H12: =IF(OR(C12="",F12=""),"",C12*F12) | I12: =IF(OR(F12="",G12=""),"",G12-F12) | J12: =IF(A12="","",IF(D12>=Umbrales!$B$3,2,0)+IF(E12<=Umbrales!$B$4,2,0)+IF(H12>=Umbrales!$B$5,2,0)+IF(I12>=Umbrales!$B$6,1,0)) | K12: =IF(A12="","",IF(J12>=6,"Retirar",IF(J12=5,"Sacar por copa",IF(J12=4,"Visibilizar","Impulsar"))))
H13: =IF(OR(C13="",F13=""),"",C13*F13) | I13: =IF(OR(F13="",G13=""),"",G13-F13) | J13: =IF(A13="","",IF(D13>=Umbrales!$B$3,2,0)+IF(E13<=Umbrales!$B$4,2,0)+IF(H13>=Umbrales!$B$5,2,0)+IF(I13>=Umbrales!$B$6,1,0)) | K13: =IF(A13="","",IF(J13>=6,"Retirar",IF(J13=5,"Sacar por copa",IF(J13=4,"Visibilizar","Impulsar"))))
H14: =IF(OR(C14="",F14=""),"",C14*F14) | I14: =IF(OR(F14="",G14=""),"",G14-F14) | J14: =IF(A14="","",IF(D14>=Umbrales!$B$3,2,0)+IF(E14<=Umbrales!$B$4,2,0)+IF(H14>=Umbrales!$B$5,2,0)+IF(I14>=Umbrales!$B$6,1,0)) | K14: =IF(A14="","",IF(J14>=6,"Retirar",IF(J14=5,"Sacar por copa",IF(J14=4,"Visibilizar","Impulsar"))))
H15: =IF(OR(C15="",F15=""),"",C15*F15) | I15: =IF(OR(F15="",G15=""),"",G15-F15) | J15: =IF(A15="","",IF(D15>=Umbrales!$B$3,2,0)+IF(E15<=Umbrales!$B$4,2,0)+IF(H15>=Umbrales!$B$5,2,0)+IF(I15>=Umbrales!$B$6,1,0)) | K15: =IF(A15="","",IF(J15>=6,"Retirar",IF(J15=5,"Sacar por copa",IF(J15=4,"Visibilizar","Impulsar"))))
H16: =IF(OR(C16="",F16=""),"",C16*F16) | I16: =IF(OR(F16="",G16=""),"",G16-F16) | J16: =IF(A16="","",IF(D16>=Umbrales!$B$3,2,0)+IF(E16<=Umbrales!$B$4,2,0)+IF(H16>=Umbrales!$B$5,2,0)+IF(I16>=Umbrales!$B$6,1,0)) | K16: =IF(A16="","",IF(J16>=6,"Retirar",IF(J16=5,"Sacar por copa",IF(J16=4,"Visibilizar","Impulsar"))))
... H150: =IF(OR(C150="",F150=""),"",C150*F150) | I150: =IF(OR(F150="",G150=""),"",G150-F150) | J150: =IF(A150="","",IF(D150>=Umbrales!$B$3,2,0)+IF(E150<=Umbrales!$B$4,2,0)+IF(H150>=Umbrales!$B$5,2,0)+IF(I150>=Umbrales!$B$6,1,0)) | K150: =IF(A150="","",IF(J150>=6,"Retirar",IF(J150=5,"Sacar por copa",IF(J150=4,"Visibilizar","Impulsar"))))

Sheet Resumen
A1: Métrica | B1: Valor
A2: Referencias analizadas | B2: =COUNTIF(Análisis!A2:A150,"<>")
A3: Capital inmovilizado total (€) | B3: =SUM(Análisis!H2:H150)
A4: Referencias score >= 6 | B4: =COUNTIF(Análisis!J2:J150,">=6")
A5: Referencias score 4-5 | B5: =COUNTIFS(Análisis!J2:J150,">=4",Análisis!J2:J150,"<6")
